urlographer
