Metadata-Version: 1.1
Name: django-urlographer
Version: 0.9.0
Summary: URL mapper for django
Home-page: https://github.com/ConsumerAffairs/django-urlographer
Author: Josh Mize
Author-email: jmize@consumeraffairs.com
License: Apache License 2.0
Platform: UNKNOWN
Classifier: Development Status :: 4 - Beta
Classifier: Environment :: Web Environment
Classifier: Framework :: Django
Classifier: Intended Audience :: Developers
Classifier: License :: OSI Approved :: Apache Software License
Classifier: Operating System :: OS Independent
Classifier: Programming Language :: Python
Classifier: Programming Language :: Python :: 2
Classifier: Programming Language :: Python :: 2.7
Classifier: Topic :: Software Development :: Libraries :: Python Modules
